flasklaunch/__init__.py
flasklaunch/cli.py
flasklaunch/commands.py
flasklaunch/exceptions.py
flasklaunch/version.py
flasklaunch/templates/app/web/templates/example.html
flasklaunch/templates/app/web/templates/index.html
flasklaunch/templates-basic/.env
flasklaunch/templates-basic/README.md
flasklaunch/templates-basic/run.py
flasklaunch/templates-basic/settings.yaml
flasklaunch/templates-basic/app/__init__.py
flasklaunch/templates-basic/app/config/__init__.py
flasklaunch/templates-basic/app/config/configuration.py
flasklaunch/templates-basic/app/config/extensions.py
flasklaunch/templates-basic/app/config/logging_config.py
flasklaunch/templates-basic/app/extensions/__init__.py
flasklaunch/tests/__init__.py
flasklaunch/utils/__init__.py
flasklaunch-0.1.2.dist-info/LICENSE
flasklaunch-0.1.2.dist-info/METADATA
flasklaunch-0.1.2.dist-info/WHEEL
flasklaunch-0.1.2.dist-info/entry_points.txt
flasklaunch-0.1.2.dist-info/top_level.txt
flasklaunch-0.1.2.dist-info/RECORD
